TensorflowJuanjiShenjingwangluoShiyongZhinanChuyi/README.md
TensorflowJuanjiShenjingwangluoShiyongZhinanChuyi/__init__.py
TensorflowJuanjiShenjingwangluoShiyongZhinanChuyi/__main__.py
TensorflowJuanjiShenjingwangluoShiyongZhinanChuyi/file.epub
TensorflowJuanjiShenjingwangluoShiyongZhinanChuyi/index.html
TensorflowJuanjiShenjingwangluoShiyongZhinanChuyi/css/__init__.py
TensorflowJuanjiShenjingwangluoShiyongZhinanChuyi/css/annotations.css
TensorflowJuanjiShenjingwangluoShiyongZhinanChuyi/css/main.css
TensorflowJuanjiShenjingwangluoShiyongZhinanChuyi/css/normalize.css
TensorflowJuanjiShenjingwangluoShiyongZhinanChuyi/css/popup.css
TensorflowJuanjiShenjingwangluoShiyongZhinanChuyi/font/__init__.py
TensorflowJuanjiShenjingwangluoShiyongZhinanChuyi/font/fontello.eot
TensorflowJuanjiShenjingwangluoShiyongZhinanChuyi/font/fontello.svg
TensorflowJuanjiShenjingwangluoShiyongZhinanChuyi/font/fontello.ttf
TensorflowJuanjiShenjingwangluoShiyongZhinanChuyi/font/fontello.woff
TensorflowJuanjiShenjingwangluoShiyongZhinanChuyi/img/__init__.py
TensorflowJuanjiShenjingwangluoShiyongZhinanChuyi/img/annotator-glyph-sprite.png
TensorflowJuanjiShenjingwangluoShiyongZhinanChuyi/img/annotator-icon-sprite.png
TensorflowJuanjiShenjingwangluoShiyongZhinanChuyi/img/apple-touch-icon.png
TensorflowJuanjiShenjingwangluoShiyongZhinanChuyi/img/cancelfullscreen.png
TensorflowJuanjiShenjingwangluoShiyongZhinanChuyi/img/close.png
TensorflowJuanjiShenjingwangluoShiyongZhinanChuyi/img/fullscreen.png
TensorflowJuanjiShenjingwangluoShiyongZhinanChuyi/img/loader.gif
TensorflowJuanjiShenjingwangluoShiyongZhinanChuyi/img/menu-icon.png
TensorflowJuanjiShenjingwangluoShiyongZhinanChuyi/img/save.png
TensorflowJuanjiShenjingwangluoShiyongZhinanChuyi/img/saved.png
TensorflowJuanjiShenjingwangluoShiyongZhinanChuyi/img/settings-s.png
TensorflowJuanjiShenjingwangluoShiyongZhinanChuyi/img/settings.png
TensorflowJuanjiShenjingwangluoShiyongZhinanChuyi/img/star.png
tensorflow_juanji_shenjingwangluo_shiyong_zhinan_chuyi-2024.3.5.0.dist-info/METADATA
tensorflow_juanji_shenjingwangluo_shiyong_zhinan_chuyi-2024.3.5.0.dist-info/WHEEL
tensorflow_juanji_shenjingwangluo_shiyong_zhinan_chuyi-2024.3.5.0.dist-info/entry_points.txt
tensorflow_juanji_shenjingwangluo_shiyong_zhinan_chuyi-2024.3.5.0.dist-info/top_level.txt
tensorflow_juanji_shenjingwangluo_shiyong_zhinan_chuyi-2024.3.5.0.dist-info/RECORD
